{
    "packages": [
      {
        "name": "community_nrf52",
        "maintainer": "Pierre Constantineau",
        "websiteURL": "https://github.com/jpconstantineau/Community_nRF52_Arduino",
        "email": "pierre@jpconstantineau.com",
        "help": {
          "online": "https://github.com/jpconstantineau/Community_nRF52_Arduino"
        },
        "platforms": [
            {
                "name": "Community Add on to Adafruit nRF52",
                "architecture": "nrf52",
                "version": "",
                "category": "Contributed",
                "url": "",
                "archiveFileName": "",
                "checksum": "",
                "size": "",
                "help": {
                "online": "https://github.com/jpconstantineau/Community_nRF52_Arduino/wiki"
                },
                "boards": [
                { "name": "Nordic PCA10056"},
                { "name": "Nordic PCA10059"},
                { "name": "BlueMicro nrf52840"}
                ],
                "toolsDependencies": [
                {
                "packager": "adafruit",
                "name": "arm-none-eabi-gcc",
                "version": "9-2019q4"
                },
                {
                "packager": "adafruit",
                "name": "nrfjprog",
                "version": "9.4.0"
                }
                ]
            }
        ],
        "tools": []
      }
    ]
  }